commitgpt/__init__.py
commitgpt/__main__.py
commitgpt/gitop.py
commitgpt/gpt.py
commitgpt/main.py
commitgpt/prompts.py
commitgpt/test_gitop.py
commitgpt/test_gpt.py
commitgpt/test_update.py
commitgpt/update.py
commitgpt-1.1.0.dist-info/LICENSE
commitgpt-1.1.0.dist-info/METADATA
commitgpt-1.1.0.dist-info/WHEEL
commitgpt-1.1.0.dist-info/entry_points.txt
commitgpt-1.1.0.dist-info/RECORD
