Metadata-Version: 2.1
Name: commitgpt
Version: 1.1.0
Summary: commitgpt assists developers in generating high-quality commit messages for their version control systems, such as git.
License: LICENSE
Author: Rodney Osodo
Author-email: socials@rodneyosodo.com
Requires-Python: >=3.8.1,<4.0.0
Classifier: License :: Other/Proprietary License
Classifier: Programming Language :: Python :: 3
Classifier: Programming Language :: Python :: 3.9
Classifier: Programming Language :: Python :: 3.10
Classifier: Programming Language :: Python :: 3.11
Requires-Dist: coveralls (>=3.3.1,<4.0.0)
Requires-Dist: feedparser (>=6.0.10,<7.0.0)
Requires-Dist: gitpython (>=3.1.32,<4.0.0)
Requires-Dist: langchain (>=0.0.329,<0.0.345)
Requires-Dist: openai (>=0.27.10,<1.4.0)
Requires-Dist: packaging (>=23.2,<24.0)
Requires-Dist: pytest (>=7.4.1,<8.0.0)
Requires-Dist: tiktoken (>=0.5.1,<0.6.0)
Requires-Dist: typer[all] (>=0.9.0,<0.10.0)
Requires-Dist: unstructured (>=0.10.28,<0.12.0)
